py_code_meli/__init__.py
py_code_meli/validator.py
py_code_meli-0.1.3.dist-info/WHEEL
py_code_meli-0.1.3.dist-info/METADATA
py_code_meli-0.1.3.dist-info/RECORD
