Metadata-Version: 2.1
Name: py-code-meli
Version: 0.1.3
Summary: This python package gives you a simple method that you can validate code meli (Iranian National Code) with it.
Home-page: https://github.com/rabbitix/py_code_meli
License: MIT
Keywords: python,code meli,code_meli
Author: ali
Author-email: lmntrix.afr@gmail.com
Requires-Python: >=3.8,<4.0
Classifier: License :: OSI Approved :: MIT License
Classifier: Programming Language :: Python :: 3
Classifier: Programming Language :: Python :: 3.10
Classifier: Programming Language :: Python :: 3.8
Classifier: Programming Language :: Python :: 3.9
Classifier: Topic :: Software Development :: Libraries :: Python Modules
Project-URL: Repository, https://github.com/rabbitix/py_code_meli
